{"kind": "tau-crystal-receipt", "version": "1.2.0", "process": {"id": "PO-2025-0912-00421", "domain": "P2P", "segment": "3WM.matched", "prev_manifest": "sha256:4da10902a9a139498bd23290d2b3ef0853188a8bab4cd9df0537a0f2a74f7e91"}, "tau": {"t": [0.0, 0.0, 0.06, 0.12, 0.18], "clock": "Chebyshev-decay", "params": {"tau_min": 0.06, "slope": 0.3}}, "residue": {"R_norm": 0.6, "D_norm": 0.5196152422706631, "kappa": 0.1591549431, "qcro": [{"t": 0.0, "mode": "nominal", "amp": 0.0}, {"t": 0.06, "mode": "nominal", "amp": 0.0}, {"t": 0.12, "mode": "split_receipt", "amp": 0.6}, {"t": 0.18, "mode": "nominal", "amp": 0.0}]}, "witness": {"events_sha": "sha256:eb2e2640ac0273dbd87fa5c4b170be31151e275725cc90a59138d2b0b67cc8c2", "pivot_transcript": "sha256:e3b0c44298fc1c149afbf4c8996fb92427ae41e4649b934ca495991b7852b855", "rank_signature": {"p": 2147482951, "rank": 6}}, "sustainability": {}, "attest": {"merkle_root": "sha256:c477eede5f470ab0fc5781c39e6e324b0f88c757a7c7e98b110e67c357a8ed37", "signed_by": "", "timestamp": "2025-09-06T04:53:57Z"}}
